cratedb_mcp/__init__.py
cratedb_mcp/__main__.py
cratedb_mcp/constants.py
orange_cratedb_mcp-0.0.1.dist-info/licenses/LICENSE
orange_cratedb_mcp-0.0.1.dist-info/METADATA
orange_cratedb_mcp-0.0.1.dist-info/WHEEL
orange_cratedb_mcp-0.0.1.dist-info/top_level.txt
orange_cratedb_mcp-0.0.1.dist-info/RECORD
